gneiss/__init__.py
gneiss/_model.py
gneiss/balances.py
gneiss/sort.py
gneiss/sparse.py
gneiss/util.py
gneiss/cluster/__init__.py
gneiss/cluster/_gaussian.py
gneiss/cluster/_pba.py
gneiss/cluster/tests/__init__.py
gneiss/cluster/tests/test_pba.py
gneiss/composition/__init__.py
gneiss/composition/_composition.py
gneiss/composition/_variance.py
gneiss/plot/__init__.py
gneiss/plot/_decompose.py
gneiss/plot/_dendrogram.py
gneiss/plot/_gmm.py
gneiss/plot/_heatmap.py
gneiss/plot/_radial.py
gneiss/plot/_regression_plot.py
gneiss/regression/__init__.py
gneiss/regression/_bayesian.py
gneiss/regression/_mixedlm.py
gneiss/regression/_model.py
gneiss/regression/_ols.py
gneiss/regression/tests/__init__.py
gneiss/regression/tests/test_mixedlm.py
gneiss/regression/tests/test_model.py
gneiss/regression/tests/test_ols.py
gneiss/sim/__init__.py
gneiss/tests/__init__.py
gneiss/tests/test_balances.py
gneiss/tests/test_model.py
gneiss/tests/test_sort.py
gneiss/tests/test_util.py
gneiss-0.4.4.dist-info/DESCRIPTION.rst
gneiss-0.4.4.dist-info/METADATA
gneiss-0.4.4.dist-info/RECORD
gneiss-0.4.4.dist-info/WHEEL
gneiss-0.4.4.dist-info/metadata.json
gneiss-0.4.4.dist-info/top_level.txt
