Metadata-Version: 2.0
Name: gneiss
Version: 0.4.4
Summary: Compositional data analysis tools and visualizations
Home-page: UNKNOWN
Author: gneiss development team
Author-email: jamietmorton@gmail.com
License: BSD
Platform: UNKNOWN
Classifier: Development Status :: 4 - Beta
Classifier: License :: OSI Approved :: BSD License
Classifier: Topic :: Software Development :: Libraries
Classifier: Topic :: Scientific/Engineering
Classifier: Topic :: Scientific/Engineering :: Bio-Informatics
Classifier: Programming Language :: Python :: 3
Classifier: Programming Language :: Python :: 3 :: Only
Classifier: Operating System :: Unix
Classifier: Operating System :: POSIX
Classifier: Operating System :: MacOS :: MacOS X
Requires-Dist: IPython (>=3.2.0)
Requires-Dist: matplotlib (>=1.4.3)
Requires-Dist: numpy (>=1.9.2)
Requires-Dist: pandas (>=0.18.0)
Requires-Dist: scipy (>=0.15.1)
Requires-Dist: nose (>=1.3.7)
Requires-Dist: scikit-bio (==0.5.1)
Requires-Dist: statsmodels (>=0.8.0)
Requires-Dist: biom-format
Requires-Dist: seaborn
